{"songs": [{"title": "Runnin\u2019 On E (Alt. Version)", "album": null, "year": null, "lyrics": "[Intro: 2Pac]\nThe police comin' nigga\nGet out of there!\n\n[Hook: 2Pac]\nIf you a bad boy then you die\nWestside outlawz when we ride, get me high\nThey fucked up when they robbed me\nPut another contract on Mobb Deep\nIf you a bad boy then you die\nWestside outlawz when we ride, get me high\nThey fucked up when they robbed me\nPut another contract on Mobb Deep\n\n[Verse 1: Napoleon]\nRunnin' through these niggas like a runnin' back\nWith my Outlaw pack\nDon\u2019t make me handle your head, so I proceed\nYoung and learn how to act\nWe on the mad for this cash, I left some dead in the back\nWe leave 'em burnt in our path, we put them holes to they head\nThe game turned on \u2019em, we got the word, then we rolled on \u2019em\nDid him so bad, he thought Jesus took his soul from \u2019em\nWe cold on \u2019em, told him we gon\u2019 mash this way\nS.O.S., shoot on sight, might take the pressure away\n\n[Verse 2: Storm]\nYo, believe I'm a broad, breaking the front lawns\nMy army if you wit me, battle positions\nThey got the rookies holdin' quickly\nRide for me deep and dirty, copyin is sloppy\nYou got to drop me \u2018fore stop me, push the crucial to lock me\nAin't a street that you Kadafi, with my mission beside\nBorn to die a thug soldier, still ridin for Pac\nThe war ain\u2019t over, raise your guns high\nThey say it\u2019s peace? That\u2019s a lie\nSo my homies die, now tell me why?\n\n[Verse 3: 2Pac]\nNow ever since momma got fucked and papa ducked out\nLook at us, murderous thugs showin' less love in the drug house\nSimilar to savages, it's a wonder we manage\nBring chaos causin' damage on our quest for cabbage\nThey ask my style similar to cash we flaunt it\nMost wanted by the population murdered you for it\nExploit your weakness revenge flow deep without release\nCriminal orders across the waters bringin' the war to the streets\nWhy fear me, fear the shit I speak\nOnce this shit drop it's heard on every fuckin' street\nLike the sound of police\nWho run the streets really?\nIn every hood legends grow\nFrom the hustlaz up at Harlem to shot callers in O'\nAnd though, Congress, don't want us to progress, we stressed\nMy homie buried at an early age, hustled to death\nHis last breath, a lesson I possess like jewels\nStay thugged out keep it movin'\n\n[Verse 4: Yaki Kadafi]\nHeavyweight thugs don't budge when we stalk the streets\nSort of like chalk and narcotics when they walk the beat\nYou speak the beef pussy draw down and drop it\nHit you with 6 shots lay the law down and throw the shells in my pocket\nGettin' mines with nine cocked extortin'\nBlocks pop with 22's in my socks with the butt hangin' out the chocolate\nYou never seen time, I travel across dream crime\nMy rolls like a million dollar bill, folded with green lines\nWith my foes erased, drink my Henney straight no chasin'\nCatch my body like cases, 5 minutes from the station\n\n[Verse 5: Young Noble]\nI hit the hole like Allen Iverson with confidence\nNo finger prints that mean there was no evidence or proof that I was present\nAt the scene of the crime around 10 niggas bleed\nAfter they made this punk fag motherfucker bleed\nMoney was bloody as shit, y\u2019all niggas shoulda seen it\nBust a cap and freak with, bow down on your knees shit\nThe Glock to your head nigga, don\u2019t let inside action\nHit innocent by-standers when you blasted, shot fuckin backwards\nLittle homies puttin work for stripes\nBut is it worth your life, g-rides runnin red lights\nI wish somebody would have told me then\nSince I\u2019m an outlaw like Napolean ain\u2019t no cell they can hold me in\nCaucasian, crazy like Arabians\nHold this spot like some niggas fade me in\nHavin\u2019 the fiend\u2019s page me\nWhen they want the product nigga I got the smoke\nGot the weed and the coke what you need what you want (coke, coke)\nWhat you working with I\u2019m on some immortal shit\nOutlawz we straight hurtin shit use artillery to murder with\nPut on the block gangsta party like Pac\nLifes hard from the OX me, and my niggas on top, top\n\n[Bridge: 2Pac]\nI know the law hate me dearly, comin' for me\nWe outlaws, thugged out, niggas runnin' on E\nI know the law hate me dearly, comin' for me\nWe outlaws, thugged out, niggas runnin' on E\nI know the law hate me dearly, they comin' for me\nWe outlaws, thugged out, niggas runnin' on E\nI know the law hate me dearly, they comin' for me\nWe outlaws, thugged out, niggas runnin' on E\n\n[Verse 5: Nuttso]\nWith my Glock, quick to let it pop, fuck the law\nCarry steel cause I live on the nigga side of the law\nRidin' foes 'cause I can't let hoes catch me slippin'\nQuick to blow and dispose if you block on hittin'\nRidin' high, blazin', kryptonite got a nigga dazin'\nBurpin' and smurkin' got on enemies before I grave 'em\nRide 'em, look behind him, I see him, he slipped\nHad to stop light in a slowly night, this motherfuckin' trick\nSlide over so I can dump and put it in em\nDamn, I guess this motherfucker know that I sent it\nHit the pedal now we high speedin'\nWith the metal tryin' to make these motherfuckers die speedin'\nUp the way I seen him slow down\nShit!! I think I done bucked these hoes down\nCaught them runnin' on e, it's kind of funny to me\nThey know they was fuckin' with me but they dumb to see\n\n[Verse 6: 2Pac]\nOpen up fire watch 'em expire when my shells split 'em\nPlus all them trick niggas basically can go to hell with 'em\nFuck 'em they phony claimin' they homies but they foes\nSpeakin' on thug niggas daily, while we nailin' they hoes\nExplode boldly at my stage shows and formation\nWords are known to spray blaze as I raise my thug nation\nA crooked thought, cops get bought, no longer caught\nOut on bail, raisin' hell, nigga fuck what you thought\nDid you cry when my girl died?\nPut out the hit, politic niggas worldwide, grabbin' my dick\nI\u2019ll never learn, take away the pain with sherm\nThrowin' gas on my enemies watchin' 'em burn\nKamikaze, I\u2019m shootin' up the casket take the body\nWhip the corpse like a pi\u00f1ata and party\nHis last breath, a straight lesson I possess like jewels\nStay thugged out keep it movin'\nRunnin' on E..\nStay thugged out keep it movin'\nRunnin' on E\n\n[Outro:2Pac]\nOne time, one time for the niggas that stayed down for us\n(Runnin on E)\nSmiff and Wessun\nThe Cocoa Brovaz\nBuckshot, B.D.I\nHeltah Skeltah\n(Runnin on E)\nBoot Camp Click", "image": "https://images.genius.com/dbbdb7f208d5866d896da3ccaf431d59.681x681x1.jpg"}], "artist": "2Pac"}