{"songs": [{"title": "Tattoo Tears (Live 1996)", "album": "Live At The House Of Blues", "year": "2018-10-03", "lyrics": "[Spoken Intro: 2Pac]\nThis some new shit called \"Tattoo Tears\"\nC'mon\nUh, uh\nUh\n(Many thugs)\n(Many thugs)\n\n[Chorus]\nI said many times busters still can\u2019t see\nY'all niggas can't fuck with me\nI been, handlin stress in this shit for years\nBlazed out sheddin\u2019 tattooed tears\n\nSaid many times busters still can't see\nY'all niggas can't fuck with me\nI been, handlin stress in this shit for years\nBlazed out sheddin' tattooed tears\n\n[Verse 1]\nNow, Rock-a-bye baby, I'm thugged out and so crazy\nDon't want to hurt a soul nigga, so don't make me\nI got a dream to see my whole team in Lexus Coupes\nMy enemies dead n buried, now the stress is through\nBut that\u2019s a dream, though it seems like reality\nThere\u2019ll never be peace long as there's fiends on these Cali streets\nEven on the other side brothers die, but ride\nNiggas get high off a slow form of suicide\nHide the closest thoughts, the war is fought as casualties\nI live my life to fuckin mo\u2019, exposin tragically\nHow can we find some peace and niggas still ain't get a piece\nI know I'm probably hellbound, but we got to eat\nI'm seeing Satan infiltratin, my military mind\nMake me hustle all the time, go out for cash makin\nForgive my adversaries they don\u2019t understand what we go through\nTo become a man, we sheddin' tattoed tears\n\n[Chorus]\nI said many times busters still can't see\nY'all niggas can't fuck with me\nI been, handlin stress in this shit for years\nBlazed out sheddin' tattooed tears (Baby)\n\nI aid many times busters still can't see\nY'all niggas can't fuck with me\nI been, handlin stress in this shit for years\nBlazed out sheddin' tattooed tears\nI'm thugged out baby\n\nMany times busters still can't see (Ha, ha)\nY'all niggas can't fuck with me (Outlaw)\nI been, handlin stress' in this shit for years\nBlazed out sheddin' tattooed tears\n\n[Verse 2]\nCriminal ways of thinkin', I'm gettin' paid wit' Lincolns\nNiggas turn made victims, get my rage from a gauge hittin'\nHittin' ya back, you ain't kickin' no facts\nFakin' jacks, you and ya bitch clique could get this AK\nHold a pound four, you catch a flame from my torch\nThe game was taught, I want my name in the source\nLittle nigga, from jumpin' GZA, Now thanks to Pizzah\nI'ma tote the pistol, And slang the white coke crystal\nThe papers...\n\n[Audience Cheering]", "image": "https://images.genius.com/aceb98afaa438b9a1b348f7296ac142f.594x594x1.jpg"}], "artist": "2Pac"}